demae/__init__.py
demae/base.py
demae/logger.py
demae/util.py
demae-0.8.0.dist-info/DESCRIPTION.rst
demae-0.8.0.dist-info/METADATA
demae-0.8.0.dist-info/RECORD
demae-0.8.0.dist-info/WHEEL
demae-0.8.0.dist-info/metadata.json
demae-0.8.0.dist-info/top_level.txt
