Metadata-Version: 2.0
Name: demae
Version: 0.8.0
Summary: UNKNOWN
Home-page: https://github.com/uiureo/demae
Author: Kazato Sugimoto
Author-email: kazato.sugimoto@gmail.com
License: UNKNOWN
Keywords: demae
Platform: UNKNOWN
Classifier: Programming Language :: Python :: 3.3
Classifier: Programming Language :: Python :: 3.4
Classifier: Programming Language :: Python :: 3.5
Requires-Dist: boto3
Requires-Dist: pandas (<0.20)
Requires-Dist: psycopg2
